{
  "date": "2020-04-15",
  "sort_key": "2020-04-15T17:08:36+00:00",
  "description": "Prime Minister Justin Trudeau has announced more flexible rules for claiming the Canada emergency response benefit (CERB) in response to critics who pointed out the initial rules excluded too many people, including those working reduced hours.\n",
  "title": "Part-time, contract and seasonal workers now qualify for CERB | Special coverage",
  "id": "UExleUpQSGJSbkdhWXhMeWJibFhqTWJnaVBkdDZoaE83VS44Mjc5REFBRUE2MTdFRDU0",
  "captions_url": "https://www.youtube.com/api/timedtext?v=UExleUpQSGJSbkdhWXhMeWJibFhqTWJnaVBkdDZoaE83VS44Mjc5REFBRUE2MTdFRDU0&lang=en&name=CC1"
}